{
  "type": "minecraft:chest",
  "pools": [
    {
      "rolls": {
        "min": 2.0,
        "max": 8.0,
        "type": "minecraft:uniform"
      },
      "entries": [
        {
          "type": "minecraft:item",
          "weight": 15,
          "functions": [
            {
              "function": "minecraft:set_count",
              "count": {
                "min": 1.0,
                "max": 6.0,
                "type": "minecraft:uniform"
              }
            }
          ],
          "name": "minecraft:foul_berries"
        },
        {
          "type": "minecraft:item",
          "weight": 10,
          "functions": [
            {
              "function": "minecraft:set_count",
              "count": {
                "min": 1.0,
                "max": 3.0,
                "type": "minecraft:uniform"
              }
            }
          ],
          "name": "minecraft:snail_slime"
        },
        {
          "type": "minecraft:item",
          "weight": 10,
          "functions": [
            {
              "function": "minecraft:set_count",
              "count": {
                "min": 1.0,
                "max": 4.0,
                "type": "minecraft:uniform"
              }
            }
          ],
          "name": "minecraft:sugar"
        },
        {
          "type": "minecraft:item",
          "weight": 5,
          "functions": [
            {
              "function": "minecraft:set_count",
              "count": {
                "min": 1.0,
                "max": 3.0,
                "type": "minecraft:uniform"
              }
            }
          ],
          "name": "minecraft:gunpowder"
        },
        {
          "type": "minecraft:item",
          "weight": 3,
          "functions": [
            {
              "function": "minecraft:set_count",
              "count": {
                "min": 1.0,
                "max": 2.0,
                "type": "minecraft:uniform"
              }
            }
          ],
          "name": "minecraft:glass_bottle"
        },
        {
          "type": "minecraft:item",
          "weight": 10,
          "functions": [
            {
              "function": "minecraft:set_count",
              "count": {
                "min": 2.0,
                "max": 5.0,
                "type": "minecraft:uniform"
              }
            }
          ],
          "name": "minecraft:wheat"
        },
        {
          "type": "minecraft:item",
          "weight": 10,
          "functions": [
            {
              "function": "minecraft:set_count",
              "count": {
                "min": 2.0,
                "max": 4.0,
                "type": "minecraft:uniform"
              }
            }
          ],
          "name": "minecraft:carrot"
        },
        {
          "type": "minecraft:item",
          "weight": 5,
          "name": "minecraft:sap_bottle"
        },
        {
          "type": "minecraft:item",
          "weight": 5,
          "name": "minecraft:spider_eye"
        },
        {
          "type": "minecraft:item",
          "weight": 5,
          "name": "minecraft:pumpkin"
        },
        {
          "type": "minecraft:item",
          "weight": 2,
          "functions": [
            {
              "function": "minecraft:set_count",
              "count": {
                "min": 2.0,
                "max": 4.0,
                "type": "minecraft:uniform"
              }
            }
          ],
          "name": "minecraft:glowstone_dust"
        }
      ]
    }
  ]
}